README.md
setup.py
adafruit_nrfutil.egg-info/PKG-INFO
adafruit_nrfutil.egg-info/SOURCES.txt
adafruit_nrfutil.egg-info/dependency_links.txt
adafruit_nrfutil.egg-info/entry_points.txt
adafruit_nrfutil.egg-info/not-zip-safe
adafruit_nrfutil.egg-info/requires.txt
adafruit_nrfutil.egg-info/top_level.txt
nordicsemi/__init__.py
nordicsemi/__main__.py
nordicsemi/exceptions.py
nordicsemi/version.py
nordicsemi/bluetooth/__init__.py
nordicsemi/bluetooth/hci/__init__.py
nordicsemi/bluetooth/hci/codec.py
nordicsemi/bluetooth/hci/slip.py
nordicsemi/bluetooth/hci/tests/__init__.py
nordicsemi/bluetooth/hci/tests/test_codec.py
nordicsemi/dfu/__init__.py
nordicsemi/dfu/crc16.py
nordicsemi/dfu/dfu.py
nordicsemi/dfu/dfu_transport.py
nordicsemi/dfu/dfu_transport_ble.py
nordicsemi/dfu/dfu_transport_serial.py
nordicsemi/dfu/init_packet.py
nordicsemi/dfu/manifest.py
nordicsemi/dfu/model.py
nordicsemi/dfu/nrfhex.py
nordicsemi/dfu/package.py
nordicsemi/dfu/signing.py
nordicsemi/dfu/util.py
nordicsemi/dfu/intelhex/__init__.py
nordicsemi/dfu/intelhex/compat.py
nordicsemi/dfu/intelhex/getsizeof.py
nordicsemi/dfu/tests/__init__.py
nordicsemi/dfu/tests/test_dfu_transport_serial.py
nordicsemi/dfu/tests/test_init_packet.py
nordicsemi/dfu/tests/test_manifest.py
nordicsemi/dfu/tests/test_nrfhex.py
nordicsemi/dfu/tests/test_package.py
nordicsemi/dfu/tests/test_signing.py
nordicsemi/utility/__init__.py
nordicsemi/utility/target_registry.py
nordicsemi/utility/tests/__init__.py
nordicsemi/utility/tests/test_target_registry.py