Metadata-Version: 2.1
Name: adafruit-nrfutil
Version: 0.5.3.post13
Summary: Python 3 version of Nordic Semiconductor nrfutil utility and Python library (modified by Adafruit)
Home-page: https://github.com/adafruit/Adafruit_nRF52_nrfutil
Author: Nordic Semiconductor ASA (modified by Adafruit Industries LLC)
Author-email: circuitpython@adafruit.com
License: Nordic Semicondictor proprietary license
Keywords: nordic nrf52 ble bluetooth dfu ota softdevice serialization nrfutil pc-nrfutil adafruit circuitpython
Platform: UNKNOWN
Classifier: Intended Audience :: Developers
Classifier: Operating System :: MacOS
Classifier: Operating System :: Microsoft :: Windows
Classifier: Operating System :: POSIX :: Linux
Classifier: Topic :: System :: Networking
Classifier: Topic :: System :: Hardware :: Hardware Drivers
Classifier: Topic :: Software Development :: Embedded Systems
Classifier: License :: Other/Proprietary License
Classifier: Programming Language :: Python :: 3.5
